[
    {
        "_id": "nuDxPWtN6WU1UDO",
        "bankruptcy": {},
        "death": {},
        "dnc": {},
        "emails": [],
        "mailingAddress": {
            "street": "3471 Fernside Pl",
            "city": "Cincinnati",
            "state": "OH",
            "zip": "45207",
            "hash": "4ebd0621cd58e14125b485c2048c9bc9"
        },
        "name": {
            "first": "Mary",
            "last": "Martin"
        },
        "phoneNumbers": [
            {
                "number": "5132814892",
                "carrier": "CINCINNATI BELL",
                "type": "Land Line",
                "tested": true,
                "reachable": true,
                "dnc": true,
                "score": 100
            },
            {
                "number": "5132812973",
                "carrier": "CINCINNATI BELL",
                "type": "Land Line",
                "tested": false,
                "reachable": false,
                "dnc": false,
                "score": 95
            },
            {
                "number": "5139617054",
                "carrier": "CINCINNATI BELL",
                "type": "Land Line",
                "tested": true,
                "reachable": true,
                "dnc": true,
                "score": 90
            },
            {
                "number": "5134981071",
                "carrier": "CELLCO PARTNERSHIP DBA VERIZON WIRELESS - OH",
                "type": "Mobile",
                "tested": true,
                "reachable": true,
                "dnc": true,
                "score": 85
            },
            {
                "number": "5132814227",
                "carrier": "TIME WARNER CABLE INFORMATION SVCS (OHIO) - OH",
                "type": "Land Line",
                "tested": false,
                "reachable": true,
                "dnc": false,
                "score": 80
            },
            {
                "number": "5136318134",
                "carrier": "CINCINNATI BELL",
                "type": "Land Line",
                "tested": false,
                "reachable": false,
                "dnc": false,
                "score": 75
            }
        ],
        "litigator": false,
        "propertyAddress": {
            "houseNumber": "3471",
            "street": "3471 Fernside Pl",
            "city": "Cincinnati",
            "county": "Hamilton",
            "state": "OH",
            "zip": "45207",
            "zipPlus4": "1420",
            "formattedStreet": "Fernside Pl",
            "streetNoUnit": "3471 Fernside Pl",
            "hash": "4ebd0621cd58e14125b485c2048c9bc9"
        },
        "involuntaryLien": {},
        "property": {
            "address": {
                "houseNumber": "3471",
                "street": "3471 Fernside Pl",
                "city": "Cincinnati",
                "county": "Hamilton",
                "state": "OH",
                "zip": "45207",
                "zipPlus4": "1420",
                "hash": "4ebd0621cd58e14125b485c2048c9bc9",
                "latitude": 39.1427045,
                "longitude": -84.4769785,
                "countyFipsCode": "39061",
                "formattedStreet": "Fernside Pl",
                "streetNoUnit": "3471 Fernside Pl",
                "cityAliases": [
                    "cincinnati"
                ],
                "geoStatus": "Rooftop"
            },
            "absenteeOwner": true,
            "vacant": false,
            "owner": {
                "name": {
                    "first": "Cincinnati Metropolitan Housing Authority",
                    "last": null
                },
                "mailingAddress": {
                    "houseNumber": "1635",
                    "street": "1635 Western Ave",
                    "city": "Cincinnati",
                    "county": "Hamilton",
                    "state": "OH",
                    "zip": "45214",
                    "formattedStreet": "Western Ave",
                    "streetNoUnit": "1635 Western Ave",
                    "hash": "db66c6303b5e73fd1f4bfb0701efe261",
                    "zipPlus4": "2001"
                }
            }
        },
        "meta": {
            "matched": true,
            "secondaryMatch": true,
            "secondaryMatchType": "property-address-mailing-address",
            "error": false
        }
    },
    {
        "_id": "AobcrP1ju0k9DTS",
        "bankruptcy": {},
        "death": {},
        "dnc": {},
        "emails": [
            {
                "email": "cronenc@gmail.com"
            },
            {
                "email": "davetzap@one.net"
            },
            {
                "email": "cronenc@aol.com"
            },
            {
                "email": "cronenc@bp.com"
            },
            {
                "email": "dave@gaslightproperty.com"
            },
            {
                "email": "hellokittyfun@hotmail.com"
            },
            {
                "email": "miyarasuta@yahoo.com"
            }
        ],
        "mailingAddress": {
            "houseNumber": "310",
            "street": "310 Terrace Ave",
            "city": "Cincinnati",
            "county": "Hamilton",
            "state": "OH",
            "zip": "45220",
            "zipPlus4": "2078",
            "formattedStreet": "Terrace Ave",
            "streetNoUnit": "310 Terrace Ave",
            "hash": "19eeb508e8a7a1eeee758e1b5da2e3e9"
        },
        "name": {
            "first": "David",
            "last": "Taylor"
        },
        "phoneNumbers": [
            {
                "number": "5138616000",
                "carrier": "LEVEL 3 COMMUNICATIONS- LLC - OH",
                "type": "Land Line",
                "tested": false,
                "reachable": true,
                "dnc": false,
                "score": 100,
                "firstReportedDate": "2008-06-06T00:00:00.000Z",
                "lastReportedDate": "2021-07-01T00:00:00.000Z"
            },
            {
                "number": "5138616360",
                "carrier": "LEVEL 3 COMMUNICATIONS- LLC - OH",
                "type": "Land Line",
                "tested": true,
                "reachable": true,
                "dnc": true,
                "score": 95,
                "firstReportedDate": "2008-06-06T00:00:00.000Z",
                "lastReportedDate": "2010-12-15T00:00:00.000Z"
            },
            {
                "number": "5137035561",
                "carrier": "NEW CINGULAR WIRELESS PCS- LLC - IL",
                "type": "Mobile",
                "tested": false,
                "reachable": true,
                "dnc": false,
                "score": 90,
                "firstReportedDate": "2008-06-06T00:00:00.000Z",
                "lastReportedDate": "2010-12-15T00:00:00.000Z"
            },
            {
                "number": "5138612366",
                "carrier": "CINCINNATI BELL",
                "type": "Land Line",
                "tested": false,
                "reachable": false,
                "dnc": false,
                "score": 85,
                "firstReportedDate": "2000-10-01T00:00:00.000Z",
                "lastReportedDate": "2010-12-15T00:00:00.000Z"
            },
            {
                "number": "5138611549",
                "carrier": "CINCINNATI BELL",
                "type": "Land Line",
                "tested": true,
                "reachable": true,
                "dnc": true,
                "score": 80,
                "firstReportedDate": "2000-11-01T00:00:00.000Z",
                "lastReportedDate": "2008-06-06T00:00:00.000Z"
            },
            {
                "number": "5138616362",
                "carrier": "LEVEL 3 COMMUNICATIONS- LLC - OH",
                "type": "Land Line",
                "tested": false,
                "reachable": true,
                "dnc": false,
                "score": 75,
                "firstReportedDate": "1999-09-01T00:00:00.000Z",
                "lastReportedDate": "1999-09-15T00:00:00.000Z"
            },
            {
                "number": "5133126348",
                "carrier": "NEW CINGULAR WIRELESS PCS- LLC - IL",
                "type": "Mobile",
                "tested": true,
                "reachable": true,
                "dnc": true,
                "score": 70,
                "firstReportedDate": "2010-01-31T00:00:00.000Z",
                "lastReportedDate": "2010-01-31T00:00:00.000Z"
            },
            {
                "number": "5132813011",
                "carrier": "CINCINNATI BELL",
                "type": "Land Line",
                "tested": false,
                "reachable": false,
                "dnc": false,
                "score": 65,
                "firstReportedDate": "2016-03-16T00:00:00.000Z",
                "lastReportedDate": "2016-03-16T00:00:00.000Z"
            },
            {
                "number": "5133212224",
                "carrier": "CINCINNATI BELL",
                "type": "Land Line",
                "tested": true,
                "reachable": true,
                "dnc": true,
                "score": 60,
                "firstReportedDate": "2016-03-16T00:00:00.000Z",
                "lastReportedDate": "2016-03-16T00:00:00.000Z"
            },
            {
                "number": "5135411678",
                "carrier": "CINCINNATI BELL",
                "type": "Land Line",
                "tested": true,
                "reachable": true,
                "dnc": true,
                "score": 55,
                "firstReportedDate": "2016-03-16T00:00:00.000Z",
                "lastReportedDate": "2016-03-16T00:00:00.000Z"
            },
            {
                "number": "5136072078",
                "carrier": "CELLCO PARTNERSHIP DBA VERIZON WIRELESS - OH",
                "type": "Mobile",
                "tested": true,
                "reachable": true,
                "dnc": true,
                "score": 50,
                "firstReportedDate": "2016-03-16T00:00:00.000Z",
                "lastReportedDate": "2016-03-16T00:00:00.000Z"
            },
            {
                "number": "5138615202",
                "carrier": "CINCINNATI BELL",
                "type": "Land Line",
                "tested": false,
                "reachable": false,
                "dnc": false,
                "score": 45,
                "firstReportedDate": "2016-03-16T00:00:00.000Z",
                "lastReportedDate": "2016-03-16T00:00:00.000Z"
            }
        ],
        "litigator": false,
        "propertyAddress": {
            "houseNumber": "415",
            "street": "415 Probasco St",
            "city": "Cincinnati",
            "county": "Hamilton",
            "state": "OH",
            "zip": "45220",
            "zipPlus4": "3205",
            "formattedStreet": "Probasco St",
            "streetNoUnit": "415 Probasco St",
            "hash": "c537a1df084bd94a35ce688c76471e36"
        },
        "involuntaryLien": {},
        "property": {
            "address": {
                "houseNumber": "415",
                "street": "415 Probasco St",
                "city": "Cincinnati",
                "county": "Hamilton",
                "state": "OH",
                "zip": "45220",
                "zipPlus4": "3205",
                "hash": "c537a1df084bd94a35ce688c76471e36",
                "latitude": 39.133944,
                "longitude": -84.525513,
                "countyFipsCode": "39061",
                "formattedStreet": "Probasco St",
                "streetNoUnit": "415 Probasco St",
                "cityAliases": [
                    "cincinnati"
                ],
                "geoStatus": "Rooftop"
            },
            "equity": 626878,
            "equityPercent": 67.01,
            "absenteeOwner": true,
            "vacant": false,
            "owner": {
                "name": {
                    "first": "3015 Clifton Llc",
                    "last": null
                },
                "mailingAddress": {
                    "houseNumber": "310",
                    "street": "310 Terrace Ave Ste 200",
                    "city": "Cincinnati",
                    "county": "Hamilton",
                    "state": "OH",
                    "zip": "45220",
                    "formattedStreet": "Terrace Ave",
                    "streetNoUnit": "310 Terrace Ave",
                    "unitNumber": "200",
                    "unitType": "STE",
                    "hash": "b3e2013d74557c0003170d9bc03c4264",
                    "zipPlus4": "2078"
                }
            }
        },
        "meta": {
            "matched": true
        }
    }
]